LICENSE.md
MANIFEST.in
NOTICE
README.md
introduction.md
main.py
setup.py
markdown/__init__.py
markdown/__main__.py
markdown/blockparser.py
markdown/blockprocessors.py
markdown/etree_loader.py
markdown/inlinepatterns.py
markdown/odict.py
markdown/postprocessors.py
markdown/preprocessors.py
markdown/serializers.py
markdown/treeprocessors.py
markdown/util.py
markdown/extensions/__init__.py
markdown/extensions/abbr.py
markdown/extensions/attr_list.py
markdown/extensions/codehilite.py
markdown/extensions/def_list.py
markdown/extensions/extra.py
markdown/extensions/fenced_code.py
markdown/extensions/footnotes.py
markdown/extensions/headerid.py
markdown/extensions/html_tidy.py
markdown/extensions/meta.py
markdown/extensions/nl2br.py
markdown/extensions/rss.py
markdown/extensions/sane_lists.py
markdown/extensions/smart_strong.py
markdown/extensions/tables.py
markdown/extensions/toc.py
markdown/extensions/wikilinks.py
pygments/__init__.py
pygments/cmdline.py
pygments/console.py
pygments/filter.py
pygments/formatter.py
pygments/lexer.py
pygments/plugin.py
pygments/scanner.py
pygments/style.py
pygments/token.py
pygments/unistring.py
pygments/util.py
pygments/filters/__init__.py
pygments/formatters/__init__.py
pygments/formatters/_mapping.py
pygments/formatters/bbcode.py
pygments/formatters/html.py
pygments/formatters/img.py
pygments/formatters/latex.py
pygments/formatters/other.py
pygments/formatters/rtf.py
pygments/formatters/svg.py
pygments/formatters/terminal.py
pygments/formatters/terminal256.py
pygments/lexers/__init__.py
pygments/lexers/_asybuiltins.py
pygments/lexers/_clbuiltins.py
pygments/lexers/_lassobuiltins.py
pygments/lexers/_luabuiltins.py
pygments/lexers/_mapping.py
pygments/lexers/_openedgebuiltins.py
pygments/lexers/_phpbuiltins.py
pygments/lexers/_postgres_builtins.py
pygments/lexers/_scilab_builtins.py
pygments/lexers/_sourcemodbuiltins.py
pygments/lexers/_stan_builtins.py
pygments/lexers/_vimbuiltins.py
pygments/lexers/agile.py
pygments/lexers/asm.py
python_pydown.egg-info/PKG-INFO
python_pydown.egg-info/SOURCES.txt
python_pydown.egg-info/dependency_links.txt
python_pydown.egg-info/entry_points.txt
python_pydown.egg-info/top_level.txt
