Metadata-Version: 1.1
Name: python-pydown
Version: 0.1.0
Summary: An HTML5 presentation builder written by python
Home-page: https://github.com/isnowfy/pydown
Author: isnowfy
Author-email: UNKNOWN
License: The MIT License (MIT)
